{
  "name": "Home Customization",
  "short_name": "Customization",
  "description": "Safe Haven Home Customization sheet",
  "start_url": "/customization-sheet",
  "scope": "/customization-sheet",
  "display": "standalone",
  "orientation": "any",
  "background_color": "#ffffff",
  "theme_color": "#2f5fc4",
  "icons": [
    {
      "src": "/cs-icon-192.png",
      "sizes": "192x192",
      "type": "image/png",
      "purpose": "any maskable"
    },
    {
      "src": "/cs-icon-512.png",
      "sizes": "512x512",
      "type": "image/png",
      "purpose": "any maskable"
    }
  ]
}